LICENSE
MANIFEST.in
README.md
pyproject.toml
setup.cfg
setup.py
test/__init__.py
test/test_zenith.py
zenith_viz/__init__.py
zenith_viz/zenith_viz.py
zenith_viz.egg-info/PKG-INFO
zenith_viz.egg-info/SOURCES.txt
zenith_viz.egg-info/dependency_links.txt
zenith_viz.egg-info/not-zip-safe
zenith_viz.egg-info/top_level.txt
zenith_viz/__pycache__/__init__.cpython-310.pyc
zenith_viz/__pycache__/__init__.cpython-311.pyc
zenith_viz/__pycache__/__init__.cpython-39.pyc
zenith_viz/__pycache__/zenith_viz.cpython-311.pyc
zenith_viz/cpp/Controls.cpp
zenith_viz/cpp/Controls.hpp
zenith_viz/cpp/Engine.cpp
zenith_viz/cpp/Engine.hpp
zenith_viz/cpp/GLBoilerPlate.cpp
zenith_viz/cpp/GLBoilerPlate.hpp
zenith_viz/cpp/GLModel.cpp
zenith_viz/cpp/GLModel.hpp
zenith_viz/cpp/PythonBindings.cpp
zenith_viz/cpp/main.cpp
zenith_viz/cpp/signal_data.dat
zenith_viz/cpp/vptree.hpp
zenith_viz/cpp/glad/include/KHR/khrplatform.h
zenith_viz/cpp/glad/include/glad/gl.h
zenith_viz/cpp/glad/src/gl.c
zenith_viz/cpp/glfw/.appveyor.yml
zenith_viz/cpp/glfw/.editorconfig
zenith_viz/cpp/glfw/.git
zenith_viz/cpp/glfw/.gitattributes
zenith_viz/cpp/glfw/.gitignore
zenith_viz/cpp/glfw/.mailmap
zenith_viz/cpp/glfw/CMakeLists.txt
zenith_viz/cpp/glfw/CONTRIBUTORS.md
zenith_viz/cpp/glfw/LICENSE.md
zenith_viz/cpp/glfw/README.md
zenith_viz/cpp/glfw/.github/CODEOWNERS
zenith_viz/cpp/glfw/.github/workflows/build.yml
zenith_viz/cpp/glfw/CMake/GenerateMappings.cmake
zenith_viz/cpp/glfw/CMake/Info.plist.in
zenith_viz/cpp/glfw/CMake/cmake_uninstall.cmake.in
zenith_viz/cpp/glfw/CMake/glfw3.pc.in
zenith_viz/cpp/glfw/CMake/glfw3Config.cmake.in
zenith_viz/cpp/glfw/CMake/i686-w64-mingw32-clang.cmake
zenith_viz/cpp/glfw/CMake/i686-w64-mingw32.cmake
zenith_viz/cpp/glfw/CMake/x86_64-w64-mingw32-clang.cmake
zenith_viz/cpp/glfw/CMake/x86_64-w64-mingw32.cmake
zenith_viz/cpp/glfw/CMake/modules/FindEpollShim.cmake
zenith_viz/cpp/glfw/CMake/modules/FindOSMesa.cmake
zenith_viz/cpp/glfw/deps/getopt.c
zenith_viz/cpp/glfw/deps/getopt.h
zenith_viz/cpp/glfw/deps/linmath.h
zenith_viz/cpp/glfw/deps/nuklear.h
zenith_viz/cpp/glfw/deps/nuklear_glfw_gl2.h
zenith_viz/cpp/glfw/deps/stb_image_write.h
